{
 "1": {
  "date": "27.08.2023",
  "extensions": {
   "leaders": 0,
   "armada": 0,
   "edifice": 1,
   "cities": 0
  },
  "scoreboard": [
   [
    "row_id",
    "game_id",
    "points_type",
    "Pascal",
    "Stanley",
    "Elena",
    "Fabio",
    "Alan",
    "Rafael",
    "Leandro",
    "Yara"
   ],
   [
    1,
    1,
    "wonder",
    10,
    0,
    15,
    10,
    null,
    10,
    7,
    null
   ],
   [
    2,
    1,
    "money",
    2,
    0,
    2,
    4,
    null,
    0,
    3,
    null
   ],
   [
    3,
    1,
    "war",
    10,
    8,
    -4,
    -6,
    null,
    12,
    16,
    null
   ],
   [
    4,
    1,
    "blue_cards",
    13,
    24,
    9,
    23,
    null,
    9,
    14,
    null
   ],
   [
    5,
    1,
    "yellow_cards",
    3,
    2,
    4,
    0,
    null,
    9,
    4,
    null
   ],
   [
    6,
    1,
    "green_cards",
    16,
    0,
    0,
    1,
    null,
    1,
    0,
    null
   ],
   [
    7,
    1,
    "purple_cards",
    0,
    7,
    13,
    7,
    null,
    16,
    10,
    null
   ],
   [
    8,
    1,
    "cities",
    1,
    3,
    0,
    3,
    null,
    4,
    6,
    null
   ],
   [
    9,
    1,
    "leaders",
    null,
    null,
    null,
    null,
    null,
    null,
    null,
    null
   ],
   [
    10,
    1,
    "sea_war",
    null,
    null,
    null,
    null,
    null,
    null,
    null,
    null
   ],
   [
    11,
    1,
    "sea_cards",
    null,
    null,
    null,
    null,
    null,
    null,
    null,
    null
   ],
   [
    177,
    1,
    "sum",
    55,
    44,
    39,
    42,
    null,
    61,
    60,
    null
   ],
   [
    178,
    1,
    "ranking",
    3,
    4,
    6,
    5,
    null,
    1,
    2,
    null
   ]
  ]
 },
 "2": {
  "date": "27.08.2023",
  "extensions": {
   "leaders": 0,
   "armada": 1,
   "edifice": 0,
   "cities": 0
  },
  "scoreboard": [
   [
    "row_id",
    "game_id",
    "points_type",
    "Pascal",
    "Stanley",
    "Elena",
    "Fabio",
    "Alan",
    "Rafael",
    "Leandro",
    "Yara"
   ],
   [
    12,
    2,
    "wonder",
    0,
    0,
    3,
    3,
    null,
    12,
    10,
    null
   ],
   [
    13,
    2,
    "money",
    11,
    0,
    8,
    0,
    null,
    5,
    12,
    null
   ],
   [
    14,
    2,
    "war",
    10,
    -6,
    12,
    -3,
    null,
    13,
    16,
    null
   ],
   [
    15,
    2,
    "blue_cards",
    6,
    23,
    17,
    17,
    null,
    12,
    10,
    null
   ],
   [
    16,
    2,
    "yellow_cards",
    10,
    0,
    6,
    6,
    null,
    10,
    10,
    null
   ],
   [
    17,
    2,
    "green_cards",
    1,
    33,
    10,
    0,
    null,
    0,
    0,
    null
   ],
   [
    18,
    2,
    "purple_cards",
    0,
    0,
    17,
    9,
    null,
    9,
    16,
    null
   ],
   [
    19,
    2,
    "cities",
    null,
    null,
    null,
    null,
    null,
    null,
    null,
    null
   ],
   [
    20,
    2,
    "leaders",
    null,
    null,
    null,
    null,
    null,
    null,
    null,
    null
   ],
   [
    21,
    2,
    "sea_war",
    11,
    -6,
    0,
    5,
    null,
    7,
    0,
    null
   ],
   [
    22,
    2,
    "sea_cards",
    6,
    8,
    13,
    4,
    null,
    2,
    4,
    null
   ],
   [
    179,
    2,
    "sum",
    55,
    52,
    86,
    41,
    null,
    70,
    78,
    null
   ],
   [
    180,
    2,
    "ranking",
    4,
    5,
    1,
    6,
    null,
    3,
    2,
    null
   ]
  ]
 },
 "3": {
  "date": "27.08.2023",
  "extensions": {
   "leaders": 0,
   "armada": 0,
   "edifice": 0,
   "cities": 1
  },
  "scoreboard": [
   [
    "row_id",
    "game_id",
    "points_type",
    "Pascal",
    "Stanley",
    "Elena",
    "Fabio",
    "Alan",
    "Rafael",
    "Leandro",
    "Yara"
   ],
   [
    23,
    3,
    "wonder",
    10,
    17,
    5,
    3,
    null,
    10,
    7,
    null
   ],
   [
    24,
    3,
    "money",
    0,
    2,
    4,
    1,
    null,
    9,
    6,
    null
   ],
   [
    25,
    3,
    "war",
    11,
    0,
    10,
    -2,
    null,
    8,
    10,
    null
   ],
   [
    26,
    3,
    "blue_cards",
    0,
    34,
    13,
    4,
    null,
    12,
    20,
    null
   ],
   [
    27,
    3,
    "yellow_cards",
    3,
    6,
    8,
    0,
    null,
    0,
    4,
    null
   ],
   [
    28,
    3,
    "green_cards",
    26,
    0,
    2,
    18,
    null,
    0,
    5,
    null
   ],
   [
    29,
    3,
    "purple_cards",
    0,
    0,
    22,
    6,
    null,
    16,
    0,
    null
   ],
   [
    30,
    3,
    "cities",
    5,
    0,
    -2,
    -9,
    null,
    8,
    -2,
    null
   ],
   [
    31,
    3,
    "leaders",
    null,
    null,
    null,
    null,
    null,
    null,
    null,
    null
   ],
   [
    32,
    3,
    "sea_war",
    null,
    null,
    null,
    null,
    null,
    null,
    null,
    null
   ],
   [
    33,
    3,
    "sea_cards",
    null,
    null,
    null,
    null,
    null,
    null,
    null,
    null
   ],
   [
    181,
    3,
    "sum",
    55,
    59,
    62,
    21,
    null,
    63,
    50,
    null
   ],
   [
    182,
    3,
    "ranking",
    4,
    3,
    2,
    6,
    null,
    1,
    5,
    null
   ]
  ]
 },
 "4": {
  "date": "28.08.2023",
  "extensions": {
   "leaders": 1,
   "armada": 1,
   "edifice": 1,
   "cities": 1
  },
  "scoreboard": [
   [
    "row_id",
    "game_id",
    "points_type",
    "Pascal",
    "Stanley",
    "Elena",
    "Fabio",
    "Alan",
    "Rafael",
    "Leandro",
    "Yara"
   ],
   [
    34,
    4,
    "wonder",
    10,
    14,
    15,
    17,
    null,
    12,
    6,
    null
   ],
   [
    35,
    4,
    "money",
    6,
    8,
    7,
    5,
    null,
    12,
    5,
    null
   ],
   [
    36,
    4,
    "war",
    29,
    -1,
    -2,
    10,
    null,
    -4,
    30,
    null
   ],
   [
    37,
    4,
    "blue_cards",
    8,
    47,
    29,
    12,
    null,
    29,
    11,
    null
   ],
   [
    38,
    4,
    "yellow_cards",
    4,
    9,
    14,
    0,
    null,
    6,
    12,
    null
   ],
   [
    39,
    4,
    "green_cards",
    0,
    0,
    18,
    58,
    null,
    1,
    13,
    null
   ],
   [
    40,
    4,
    "purple_cards",
    0,
    7,
    2,
    8,
    null,
    17,
    13,
    null
   ],
   [
    41,
    4,
    "cities",
    9,
    4,
    0,
    0,
    null,
    0,
    8,
    null
   ],
   [
    42,
    4,
    "leaders",
    0,
    2,
    2,
    0,
    null,
    14,
    5,
    null
   ],
   [
    43,
    4,
    "sea_war",
    11,
    0,
    8,
    -2,
    null,
    -4,
    1,
    null
   ],
   [
    44,
    4,
    "sea_cards",
    0,
    0,
    3,
    0,
    null,
    0,
    0,
    null
   ],
   [
    183,
    4,
    "sum",
    77,
    90,
    96,
    108,
    null,
    83,
    104,
    null
   ],
   [
    184,
    4,
    "ranking",
    6,
    4,
    3,
    1,
    null,
    5,
    2,
    null
   ]
  ]
 },
 "5": {
  "date": "01.10.2023",
  "extensions": {
   "leaders": 1,
   "armada": 0,
   "edifice": 0,
   "cities": 0
  },
  "scoreboard": [
   [
    "row_id",
    "game_id",
    "points_type",
    "Pascal",
    "Stanley",
    "Elena",
    "Fabio",
    "Alan",
    "Rafael",
    "Leandro",
    "Yara"
   ],
   [
    45,
    5,
    "wonder",
    7,
    6,
    3,
    10,
    20,
    20,
    10,
    null
   ],
   [
    46,
    5,
    "money",
    0,
    21,
    18,
    12,
    9,
    6,
    8,
    null
   ],
   [
    47,
    5,
    "war",
    11,
    0,
    13,
    11,
    -1,
    15,
    -4,
    null
   ],
   [
    48,
    5,
    "blue_cards",
    0,
    3,
    22,
    5,
    23,
    10,
    22,
    null
   ],
   [
    49,
    5,
    "yellow_cards",
    0,
    4,
    15,
    6,
    3,
    0,
    0,
    null
   ],
   [
    50,
    5,
    "green_cards",
    64,
    1,
    0,
    16,
    0,
    0,
    16,
    null
   ],
   [
    51,
    5,
    "purple_cards",
    0,
    21,
    0,
    9,
    0,
    16,
    0,
    null
   ],
   [
    52,
    5,
    "cities",
    null,
    null,
    null,
    null,
    null,
    null,
    null,
    null
   ],
   [
    53,
    5,
    "leaders",
    null,
    null,
    null,
    null,
    null,
    null,
    null,
    null
   ],
   [
    54,
    5,
    "sea_war",
    null,
    null,
    null,
    null,
    null,
    null,
    null,
    null
   ],
   [
    55,
    5,
    "sea_cards",
    null,
    null,
    null,
    null,
    null,
    null,
    null,
    null
   ],
   [
    185,
    5,
    "sum",
    82,
    56,
    71,
    69,
    54,
    67,
    52,
    null
   ],
   [
    186,
    5,
    "ranking",
    1,
    5,
    2,
    3,
    6,
    4,
    7,
    null
   ]
  ]
 },
 "6": {
  "date": "19.11.2023",
  "extensions": {
   "leaders": 0,
   "armada": 1,
   "edifice": 0,
   "cities": 0
  },
  "scoreboard": [
   [
    "row_id",
    "game_id",
    "points_type",
    "Pascal",
    "Stanley",
    "Elena",
    "Fabio",
    "Alan",
    "Rafael",
    "Leandro",
    "Yara"
   ],
   [
    56,
    6,
    "wonder",
    10,
    10,
    7,
    null,
    3,
    20,
    7,
    3
   ],
   [
    57,
    6,
    "money",
    6,
    0,
    14,
    null,
    4,
    9,
    2,
    17
   ],
   [
    58,
    6,
    "war",
    -3,
    -4,
    13,
    null,
    -1,
    12,
    13,
    15
   ],
   [
    59,
    6,
    "blue_cards",
    16,
    6,
    18,
    null,
    24,
    3,
    26,
    20
   ],
   [
    60,
    6,
    "yellow_cards",
    3,
    4,
    5,
    null,
    3,
    7,
    4,
    12
   ],
   [
    61,
    6,
    "green_cards",
    2,
    76,
    1,
    null,
    4,
    0,
    1,
    1
   ],
   [
    62,
    6,
    "purple_cards",
    24,
    0,
    7,
    null,
    0,
    11,
    8,
    0
   ],
   [
    63,
    6,
    "cities",
    null,
    null,
    null,
    null,
    null,
    null,
    null,
    null
   ],
   [
    64,
    6,
    "leaders",
    null,
    null,
    null,
    null,
    null,
    null,
    null,
    null
   ],
   [
    65,
    6,
    "sea_war",
    11,
    0,
    10,
    null,
    19,
    14,
    8,
    7
   ],
   [
    66,
    6,
    "sea_cards",
    3,
    0,
    7,
    null,
    0,
    0,
    3,
    0
   ],
   [
    187,
    6,
    "sum",
    72,
    92,
    82,
    null,
    56,
    76,
    72,
    75
   ],
   [
    189,
    6,
    "ranking",
    5,
    1,
    2,
    null,
    6,
    3,
    5,
    4
   ]
  ]
 },
 "7": {
  "date": "19.11.2023",
  "extensions": {
   "leaders": 0,
   "armada": 1,
   "edifice": 0,
   "cities": 0
  },
  "scoreboard": [
   [
    "row_id",
    "game_id",
    "points_type",
    "Pascal",
    "Stanley",
    "Elena",
    "Fabio",
    "Alan",
    "Rafael",
    "Leandro",
    "Yara"
   ],
   [
    67,
    7,
    "wonder",
    7,
    3,
    null,
    20,
    10,
    0,
    3,
    10
   ],
   [
    68,
    7,
    "money",
    11,
    0,
    null,
    2,
    6,
    7,
    2,
    9
   ],
   [
    69,
    7,
    "war",
    31,
    1,
    null,
    4,
    12,
    -3,
    -6,
    11
   ],
   [
    70,
    7,
    "blue_cards",
    9,
    14,
    null,
    20,
    6,
    46,
    7,
    9
   ],
   [
    71,
    7,
    "yellow_cards",
    16,
    0,
    null,
    4,
    12,
    6,
    6,
    6
   ],
   [
    72,
    7,
    "green_cards",
    0,
    52,
    null,
    1,
    0,
    0,
    34,
    1
   ],
   [
    73,
    7,
    "purple_cards",
    0,
    0,
    null,
    17,
    9,
    7,
    15,
    12
   ],
   [
    74,
    7,
    "cities",
    null,
    null,
    null,
    null,
    null,
    null,
    null,
    null
   ],
   [
    75,
    7,
    "leaders",
    null,
    null,
    null,
    null,
    null,
    null,
    null,
    null
   ],
   [
    76,
    7,
    "sea_war",
    10,
    -1,
    null,
    0,
    6,
    -3,
    0,
    0
   ],
   [
    77,
    7,
    "sea_cards",
    1,
    6,
    null,
    10,
    8,
    10,
    8,
    2
   ],
   [
    190,
    7,
    "sum",
    85,
    75,
    null,
    78,
    69,
    70,
    69,
    60
   ],
   [
    191,
    7,
    "ranking",
    1,
    3,
    null,
    2,
    5,
    4,
    5,
    6
   ]
  ]
 },
 "8": {
  "date": "00.00.2021",
  "extensions": {
   "leaders": 0,
   "armada": 0,
   "edifice": 0,
   "cities": 0
  },
  "scoreboard": [
   [
    "row_id",
    "game_id",
    "points_type",
    "Pascal",
    "Stanley",
    "Elena",
    "Fabio",
    "Alan",
    "Rafael",
    "Leandro",
    "Yara"
   ],
   [
    78,
    8,
    "wonder",
    7,
    8,
    10,
    10,
    null,
    10,
    10,
    null
   ],
   [
    79,
    8,
    "money",
    5,
    7,
    8,
    0,
    null,
    1,
    3,
    null
   ],
   [
    80,
    8,
    "war",
    -4,
    12,
    17,
    8,
    null,
    -6,
    7,
    null
   ],
   [
    81,
    8,
    "blue_cards",
    34,
    5,
    0,
    0,
    null,
    0,
    16,
    null
   ],
   [
    82,
    8,
    "yellow_cards",
    3,
    5,
    14,
    0,
    null,
    6,
    0,
    null
   ],
   [
    83,
    8,
    "green_cards",
    0,
    9,
    0,
    33,
    null,
    31,
    1,
    null
   ],
   [
    84,
    8,
    "purple_cards",
    16,
    0,
    20,
    0,
    null,
    0,
    9,
    null
   ],
   [
    85,
    8,
    "cities",
    null,
    null,
    null,
    null,
    null,
    null,
    null,
    null
   ],
   [
    86,
    8,
    "leaders",
    null,
    null,
    null,
    null,
    null,
    null,
    null,
    null
   ],
   [
    87,
    8,
    "sea_war",
    null,
    null,
    null,
    null,
    null,
    null,
    null,
    null
   ],
   [
    88,
    8,
    "sea_cards",
    null,
    null,
    null,
    null,
    null,
    null,
    null,
    null
   ],
   [
    192,
    8,
    "sum",
    61,
    46,
    69,
    51,
    null,
    42,
    46,
    null
   ],
   [
    193,
    8,
    "ranking",
    2,
    4,
    1,
    3,
    null,
    5,
    4,
    null
   ]
  ]
 },
 "9": {
  "date": "00.00.2021",
  "extensions": {
   "leaders": 1,
   "armada": 0,
   "edifice": 0,
   "cities": 0
  },
  "scoreboard": [
   [
    "row_id",
    "game_id",
    "points_type",
    "Pascal",
    "Stanley",
    "Elena",
    "Fabio",
    "Alan",
    "Rafael",
    "Leandro",
    "Yara"
   ],
   [
    89,
    9,
    "wonder",
    10,
    10,
    null,
    10,
    null,
    6,
    10,
    null
   ],
   [
    90,
    9,
    "money",
    12,
    3,
    null,
    1,
    null,
    7,
    6,
    null
   ],
   [
    91,
    9,
    "war",
    11,
    13,
    null,
    9,
    null,
    -5,
    0,
    null
   ],
   [
    92,
    9,
    "blue_cards",
    19,
    24,
    null,
    15,
    null,
    21,
    0,
    null
   ],
   [
    93,
    9,
    "yellow_cards",
    8,
    5,
    null,
    0,
    null,
    3,
    0,
    null
   ],
   [
    94,
    9,
    "green_cards",
    0,
    0,
    null,
    10,
    null,
    10,
    34,
    null
   ],
   [
    95,
    9,
    "purple_cards",
    9,
    0,
    null,
    0,
    null,
    14,
    0,
    null
   ],
   [
    96,
    9,
    "cities",
    null,
    null,
    null,
    null,
    null,
    null,
    null,
    null
   ],
   [
    97,
    9,
    "leaders",
    16,
    0,
    null,
    9,
    null,
    4,
    0,
    null
   ],
   [
    98,
    9,
    "sea_war",
    null,
    null,
    null,
    null,
    null,
    null,
    null,
    null
   ],
   [
    99,
    9,
    "sea_cards",
    null,
    null,
    null,
    null,
    null,
    null,
    null,
    null
   ],
   [
    194,
    9,
    "sum",
    85,
    55,
    null,
    54,
    null,
    60,
    50,
    null
   ],
   [
    195,
    9,
    "ranking",
    1,
    3,
    null,
    4,
    null,
    2,
    5,
    null
   ]
  ]
 },
 "10": {
  "date": "00.00.2021",
  "extensions": {
   "leaders": 1,
   "armada": 0,
   "edifice": 0,
   "cities": 0
  },
  "scoreboard": [
   [
    "row_id",
    "game_id",
    "points_type",
    "Pascal",
    "Stanley",
    "Elena",
    "Fabio",
    "Alan",
    "Rafael",
    "Leandro",
    "Yara"
   ],
   [
    100,
    10,
    "wonder",
    6,
    10,
    null,
    10,
    null,
    0,
    20,
    null
   ],
   [
    101,
    10,
    "money",
    8,
    8,
    null,
    5,
    null,
    4,
    2,
    null
   ],
   [
    102,
    10,
    "war",
    5,
    0,
    null,
    11,
    null,
    6,
    7,
    null
   ],
   [
    103,
    10,
    "blue_cards",
    26,
    7,
    null,
    15,
    null,
    20,
    6,
    null
   ],
   [
    104,
    10,
    "yellow_cards",
    3,
    4,
    null,
    3,
    null,
    10,
    0,
    null
   ],
   [
    105,
    10,
    "green_cards",
    0,
    13,
    null,
    1,
    null,
    10,
    0,
    null
   ],
   [
    106,
    10,
    "purple_cards",
    0,
    12,
    null,
    13,
    null,
    5,
    15,
    null
   ],
   [
    107,
    10,
    "cities",
    null,
    null,
    null,
    null,
    null,
    null,
    null,
    null
   ],
   [
    108,
    10,
    "leaders",
    20,
    8,
    null,
    5,
    null,
    7,
    3,
    null
   ],
   [
    109,
    10,
    "sea_war",
    null,
    null,
    null,
    null,
    null,
    null,
    null,
    null
   ],
   [
    110,
    10,
    "sea_cards",
    null,
    null,
    null,
    null,
    null,
    null,
    null,
    null
   ],
   [
    196,
    10,
    "sum",
    68,
    62,
    null,
    63,
    null,
    62,
    53,
    null
   ],
   [
    197,
    10,
    "ranking",
    1,
    3,
    null,
    2,
    null,
    3,
    4,
    null
   ]
  ]
 },
 "11": {
  "date": "00.00.2021",
  "extensions": {
   "leaders": 1,
   "armada": 0,
   "edifice": 0,
   "cities": 0
  },
  "scoreboard": [
   [
    "row_id",
    "game_id",
    "points_type",
    "Pascal",
    "Stanley",
    "Elena",
    "Fabio",
    "Alan",
    "Rafael",
    "Leandro",
    "Yara"
   ],
   [
    111,
    11,
    "wonder",
    20,
    10,
    7,
    3,
    null,
    0,
    5,
    null
   ],
   [
    112,
    11,
    "money",
    18,
    3,
    1,
    2,
    null,
    3,
    2,
    null
   ],
   [
    113,
    11,
    "war",
    13,
    0,
    11,
    8,
    null,
    -4,
    8,
    null
   ],
   [
    114,
    11,
    "blue_cards",
    12,
    8,
    37,
    10,
    null,
    0,
    21,
    null
   ],
   [
    115,
    11,
    "yellow_cards",
    15,
    0,
    0,
    0,
    null,
    11,
    0,
    null
   ],
   [
    116,
    11,
    "green_cards",
    0,
    36,
    0,
    10,
    null,
    32,
    13,
    null
   ],
   [
    117,
    11,
    "purple_cards",
    13,
    0,
    0,
    23,
    null,
    9,
    0,
    null
   ],
   [
    118,
    11,
    "cities",
    null,
    null,
    null,
    null,
    null,
    null,
    null,
    null
   ],
   [
    119,
    11,
    "leaders",
    3,
    0,
    9,
    14,
    null,
    6,
    0,
    null
   ],
   [
    120,
    11,
    "sea_war",
    null,
    null,
    null,
    null,
    null,
    null,
    null,
    null
   ],
   [
    121,
    11,
    "sea_cards",
    null,
    null,
    null,
    null,
    null,
    null,
    null,
    null
   ],
   [
    198,
    11,
    "sum",
    94,
    57,
    65,
    70,
    null,
    57,
    49,
    null
   ],
   [
    199,
    11,
    "ranking",
    1,
    4,
    3,
    2,
    null,
    4,
    5,
    null
   ]
  ]
 },
 "12": {
  "date": "00.00.2021",
  "extensions": {
   "leaders": 1,
   "armada": 0,
   "edifice": 0,
   "cities": 0
  },
  "scoreboard": [
   [
    "row_id",
    "game_id",
    "points_type",
    "Pascal",
    "Stanley",
    "Elena",
    "Fabio",
    "Alan",
    "Rafael",
    "Leandro",
    "Yara"
   ],
   [
    122,
    12,
    "wonder",
    0,
    10,
    5,
    20,
    null,
    2,
    3,
    null
   ],
   [
    123,
    12,
    "money",
    4,
    5,
    8,
    7,
    null,
    2,
    3,
    null
   ],
   [
    124,
    12,
    "war",
    1,
    16,
    4,
    5,
    null,
    0,
    9,
    null
   ],
   [
    125,
    12,
    "blue_cards",
    2,
    4,
    34,
    3,
    null,
    6,
    36,
    null
   ],
   [
    126,
    12,
    "yellow_cards",
    7,
    9,
    0,
    8,
    null,
    0,
    0,
    null
   ],
   [
    127,
    12,
    "green_cards",
    43,
    0,
    0,
    0,
    null,
    38,
    0,
    null
   ],
   [
    128,
    12,
    "purple_cards",
    0,
    12,
    5,
    17,
    null,
    6,
    0,
    null
   ],
   [
    129,
    12,
    "cities",
    null,
    null,
    null,
    null,
    null,
    null,
    null,
    null
   ],
   [
    130,
    12,
    "leaders",
    0,
    0,
    8,
    8,
    null,
    0,
    1,
    null
   ],
   [
    131,
    12,
    "sea_war",
    null,
    null,
    null,
    null,
    null,
    null,
    null,
    null
   ],
   [
    132,
    12,
    "sea_cards",
    null,
    null,
    null,
    null,
    null,
    null,
    null,
    null
   ],
   [
    200,
    12,
    "sum",
    57,
    56,
    64,
    68,
    null,
    54,
    52,
    null
   ],
   [
    201,
    12,
    "ranking",
    3,
    4,
    2,
    1,
    null,
    5,
    6,
    null
   ]
  ]
 },
 "13": {
  "date": "00.00.2021",
  "extensions": {
   "leaders": 1,
   "armada": 0,
   "edifice": 0,
   "cities": 0
  },
  "scoreboard": [
   [
    "row_id",
    "game_id",
    "points_type",
    "Pascal",
    "Stanley",
    "Elena",
    "Fabio",
    "Alan",
    "Rafael",
    "Leandro",
    "Yara"
   ],
   [
    133,
    13,
    "wonder",
    10,
    20,
    10,
    5,
    null,
    3,
    10,
    null
   ],
   [
    134,
    13,
    "money",
    6,
    3,
    2,
    2,
    null,
    5,
    5,
    null
   ],
   [
    135,
    13,
    "war",
    2,
    0,
    4,
    18,
    null,
    -6,
    18,
    null
   ],
   [
    136,
    13,
    "blue_cards",
    37,
    0,
    16,
    18,
    null,
    12,
    2,
    null
   ],
   [
    137,
    13,
    "yellow_cards",
    7,
    0,
    0,
    6,
    null,
    0,
    10,
    null
   ],
   [
    138,
    13,
    "green_cards",
    0,
    4,
    38,
    1,
    null,
    25,
    1,
    null
   ],
   [
    139,
    13,
    "purple_cards",
    5,
    9,
    0,
    9,
    null,
    9,
    11,
    null
   ],
   [
    140,
    13,
    "cities",
    null,
    null,
    null,
    null,
    null,
    null,
    null,
    null
   ],
   [
    141,
    13,
    "leaders",
    6,
    8,
    6,
    11,
    null,
    8,
    0,
    null
   ],
   [
    142,
    13,
    "sea_war",
    null,
    null,
    null,
    null,
    null,
    null,
    null,
    null
   ],
   [
    143,
    13,
    "sea_cards",
    null,
    null,
    null,
    null,
    null,
    null,
    null,
    null
   ],
   [
    202,
    13,
    "sum",
    73,
    44,
    76,
    70,
    null,
    56,
    57,
    null
   ],
   [
    203,
    13,
    "ranking",
    2,
    6,
    1,
    3,
    null,
    5,
    4,
    null
   ]
  ]
 },
 "14": {
  "date": "00.00.2021",
  "extensions": {
   "leaders": 1,
   "armada": 0,
   "edifice": 0,
   "cities": 0
  },
  "scoreboard": [
   [
    "row_id",
    "game_id",
    "points_type",
    "Pascal",
    "Stanley",
    "Elena",
    "Fabio",
    "Alan",
    "Rafael",
    "Leandro",
    "Yara"
   ],
   [
    144,
    14,
    "wonder",
    6,
    7,
    8,
    10,
    null,
    5,
    10,
    null
   ],
   [
    145,
    14,
    "money",
    1,
    3,
    5,
    9,
    null,
    4,
    0,
    null
   ],
   [
    146,
    14,
    "war",
    12,
    7,
    11,
    -3,
    null,
    1,
    0,
    null
   ],
   [
    147,
    14,
    "blue_cards",
    23,
    3,
    15,
    0,
    null,
    23,
    23,
    null
   ],
   [
    148,
    14,
    "yellow_cards",
    0,
    0,
    0,
    7,
    null,
    4,
    0,
    null
   ],
   [
    149,
    14,
    "green_cards",
    0,
    13,
    0,
    25,
    null,
    1,
    21,
    null
   ],
   [
    150,
    14,
    "purple_cards",
    3,
    5,
    0,
    0,
    null,
    14,
    0,
    null
   ],
   [
    151,
    14,
    "cities",
    null,
    null,
    null,
    null,
    null,
    null,
    null,
    null
   ],
   [
    152,
    14,
    "leaders",
    13,
    7,
    12,
    9,
    null,
    0,
    7,
    null
   ],
   [
    153,
    14,
    "sea_war",
    null,
    null,
    null,
    null,
    null,
    null,
    null,
    null
   ],
   [
    154,
    14,
    "sea_cards",
    null,
    null,
    null,
    null,
    null,
    null,
    null,
    null
   ],
   [
    204,
    14,
    "sum",
    58,
    45,
    51,
    57,
    null,
    52,
    61,
    null
   ],
   [
    205,
    14,
    "ranking",
    2,
    6,
    5,
    3,
    null,
    4,
    1,
    null
   ]
  ]
 },
 "15": {
  "date": "00.00.2021",
  "extensions": {
   "leaders": 1,
   "armada": 0,
   "edifice": 0,
   "cities": 0
  },
  "scoreboard": [
   [
    "row_id",
    "game_id",
    "points_type",
    "Pascal",
    "Stanley",
    "Elena",
    "Fabio",
    "Alan",
    "Rafael",
    "Leandro",
    "Yara"
   ],
   [
    155,
    15,
    "wonder",
    7,
    10,
    3,
    7,
    null,
    20,
    6,
    null
   ],
   [
    156,
    15,
    "money",
    9,
    3,
    2,
    8,
    null,
    5,
    3,
    null
   ],
   [
    157,
    15,
    "war",
    -3,
    -4,
    -1,
    14,
    null,
    10,
    10,
    null
   ],
   [
    158,
    15,
    "blue_cards",
    28,
    9,
    13,
    8,
    null,
    5,
    14,
    null
   ],
   [
    159,
    15,
    "yellow_cards",
    7,
    4,
    0,
    9,
    null,
    4,
    4,
    null
   ],
   [
    160,
    15,
    "green_cards",
    0,
    10,
    61,
    0,
    null,
    10,
    0,
    null
   ],
   [
    161,
    15,
    "purple_cards",
    9,
    17,
    0,
    0,
    null,
    8,
    9,
    null
   ],
   [
    162,
    15,
    "cities",
    null,
    null,
    null,
    null,
    null,
    null,
    null,
    null
   ],
   [
    163,
    15,
    "leaders",
    11,
    4,
    0,
    8,
    null,
    0,
    3,
    null
   ],
   [
    164,
    15,
    "sea_war",
    null,
    null,
    null,
    null,
    null,
    null,
    null,
    null
   ],
   [
    165,
    15,
    "sea_cards",
    null,
    null,
    null,
    null,
    null,
    null,
    null,
    null
   ],
   [
    206,
    15,
    "sum",
    68,
    53,
    78,
    54,
    null,
    62,
    49,
    null
   ],
   [
    207,
    15,
    "ranking",
    2,
    5,
    1,
    4,
    null,
    3,
    6,
    null
   ]
  ]
 },
 "16": {
  "date": "00.00.2021",
  "extensions": {
   "leaders": 0,
   "armada": 0,
   "edifice": 0,
   "cities": 0
  },
  "scoreboard": [
   [
    "row_id",
    "game_id",
    "points_type",
    "Pascal",
    "Stanley",
    "Elena",
    "Fabio",
    "Alan",
    "Rafael",
    "Leandro",
    "Yara"
   ],
   [
    166,
    16,
    "wonder",
    0,
    10,
    7,
    20,
    null,
    5,
    3,
    null
   ],
   [
    167,
    16,
    "money",
    3,
    6,
    4,
    0,
    null,
    1,
    2,
    null
   ],
   [
    168,
    16,
    "war",
    -2,
    10,
    15,
    4,
    null,
    11,
    -4,
    null
   ],
   [
    169,
    16,
    "blue_cards",
    11,
    5,
    4,
    6,
    null,
    0,
    44,
    null
   ],
   [
    170,
    16,
    "yellow_cards",
    3,
    10,
    3,
    0,
    null,
    2,
    0,
    null
   ],
   [
    171,
    16,
    "green_cards",
    13,
    0,
    34,
    17,
    null,
    16,
    0,
    null
   ],
   [
    172,
    16,
    "purple_cards",
    29,
    0,
    0,
    8,
    null,
    0,
    0,
    null
   ],
   [
    173,
    16,
    "cities",
    null,
    null,
    null,
    null,
    null,
    null,
    null,
    null
   ],
   [
    174,
    16,
    "leaders",
    null,
    null,
    null,
    null,
    null,
    null,
    null,
    null
   ],
   [
    175,
    16,
    "sea_war",
    null,
    null,
    null,
    null,
    null,
    null,
    null,
    null
   ],
   [
    176,
    16,
    "sea_cards",
    null,
    null,
    null,
    null,
    null,
    null,
    null,
    null
   ],
   [
    208,
    16,
    "sum",
    57,
    41,
    67,
    55,
    null,
    35,
    45,
    null
   ],
   [
    209,
    16,
    "ranking",
    2,
    5,
    1,
    3,
    null,
    6,
    4,
    null
   ]
  ]
 },
 "17": {
  "date": "14.01.2024",
  "extensions": {
   "leaders": 0,
   "armada": 0,
   "edifice": 0,
   "cities": 1
  },
  "scoreboard": [
   [
    "row_id",
    "game_id",
    "points_type",
    "Pascal",
    "Stanley",
    "Elena",
    "Fabio",
    "Alan",
    "Rafael",
    "Leandro",
    "Yara"
   ],
   [
    210,
    17,
    "wonder",
    10,
    20,
    10,
    10,
    null,
    10,
    10,
    null
   ],
   [
    211,
    17,
    "money",
    0,
    1,
    11,
    6,
    null,
    9,
    4,
    null
   ],
   [
    212,
    17,
    "war",
    -2,
    -5,
    7,
    1,
    null,
    14,
    16,
    null
   ],
   [
    213,
    17,
    "blue_cards",
    4,
    12,
    9,
    35,
    null,
    11,
    13,
    null
   ],
   [
    214,
    17,
    "yellow_cards",
    0,
    8,
    17,
    0,
    null,
    7,
    0,
    null
   ],
   [
    215,
    17,
    "green_cards",
    71,
    0,
    1,
    1,
    null,
    0,
    5,
    null
   ],
   [
    216,
    17,
    "purple_cards",
    0,
    4,
    7,
    17,
    null,
    9,
    10,
    null
   ],
   [
    217,
    17,
    "cities",
    0,
    14,
    0,
    0,
    null,
    8,
    4,
    null
   ],
   [
    218,
    17,
    "leaders",
    null,
    null,
    null,
    null,
    null,
    null,
    null,
    null
   ],
   [
    219,
    17,
    "sea_war",
    null,
    null,
    null,
    null,
    null,
    null,
    null,
    null
   ],
   [
    220,
    17,
    "sea_cards",
    null,
    null,
    null,
    null,
    null,
    null,
    null,
    null
   ],
   [
    221,
    17,
    "sum",
    83,
    54,
    62,
    70,
    null,
    68,
    62,
    null
   ],
   [
    222,
    17,
    "ranking",
    1,
    5,
    4,
    2,
    null,
    3,
    4,
    null
   ]
  ]
 },
 "18": {
  "date": "14.01.2024",
  "extensions": {
   "leaders": 1,
   "armada": 0,
   "edifice": 0,
   "cities": 1
  },
  "scoreboard": [
   [
    "row_id",
    "game_id",
    "points_type",
    "Pascal",
    "Stanley",
    "Elena",
    "Fabio",
    "Alan",
    "Rafael",
    "Leandro",
    "Yara"
   ],
   [
    223,
    18,
    "wonder",
    6,
    8,
    20,
    3,
    null,
    10,
    10,
    null
   ],
   [
    224,
    18,
    "money",
    8,
    -2,
    11,
    2,
    null,
    8,
    4,
    null
   ],
   [
    225,
    18,
    "war",
    13,
    -3,
    -5,
    9,
    null,
    16,
    0,
    null
   ],
   [
    226,
    18,
    "blue_cards",
    6,
    6,
    22,
    27,
    null,
    25,
    10,
    null
   ],
   [
    227,
    18,
    "yellow_cards",
    16,
    5,
    4,
    0,
    null,
    0,
    3,
    null
   ],
   [
    228,
    18,
    "green_cards",
    10,
    40,
    0,
    37,
    null,
    0,
    31,
    null
   ],
   [
    229,
    18,
    "purple_cards",
    7,
    8,
    21,
    0,
    null,
    8,
    0,
    null
   ],
   [
    230,
    18,
    "cities",
    6,
    2,
    0,
    4,
    null,
    16,
    3,
    null
   ],
   [
    231,
    18,
    "leaders",
    9,
    0,
    4,
    0,
    null,
    5,
    5,
    null
   ],
   [
    232,
    18,
    "sea_war",
    null,
    null,
    null,
    null,
    null,
    null,
    null,
    null
   ],
   [
    233,
    18,
    "sea_cards",
    null,
    null,
    null,
    null,
    null,
    null,
    null,
    null
   ],
   [
    234,
    18,
    "sum",
    81,
    64,
    77,
    82,
    null,
    88,
    66,
    null
   ],
   [
    235,
    18,
    "ranking",
    3,
    6,
    4,
    2,
    null,
    1,
    5,
    null
   ]
  ]
 },
 "19": {
  "date": "14.01.2024",
  "extensions": {
   "leaders": 1,
   "armada": 1,
   "edifice": 0,
   "cities": 0
  },
  "scoreboard": [
   [
    "row_id",
    "game_id",
    "points_type",
    "Pascal",
    "Stanley",
    "Elena",
    "Fabio",
    "Alan",
    "Rafael",
    "Leandro",
    "Yara"
   ],
   [
    236,
    19,
    "wonder",
    20,
    3,
    7,
    10,
    null,
    6,
    10,
    null
   ],
   [
    237,
    19,
    "money",
    4,
    0,
    3,
    4,
    null,
    11,
    2,
    null
   ],
   [
    238,
    19,
    "war",
    -2,
    -8,
    7,
    9,
    null,
    17,
    17,
    null
   ],
   [
    239,
    19,
    "blue_cards",
    8,
    8,
    28,
    6,
    null,
    16,
    22,
    null
   ],
   [
    240,
    19,
    "yellow_cards",
    15,
    3,
    0,
    0,
    null,
    11,
    0,
    null
   ],
   [
    241,
    19,
    "green_cards",
    0,
    33,
    9,
    76,
    null,
    0,
    0,
    null
   ],
   [
    242,
    19,
    "purple_cards",
    13,
    0,
    9,
    0,
    null,
    13,
    11,
    null
   ],
   [
    243,
    19,
    "cities",
    null,
    null,
    null,
    null,
    null,
    null,
    null,
    null
   ],
   [
    244,
    19,
    "leaders",
    8,
    3,
    9,
    0,
    null,
    11,
    6,
    null
   ],
   [
    245,
    19,
    "sea_war",
    13,
    -1,
    9,
    -6,
    null,
    1,
    -1,
    null
   ],
   [
    246,
    19,
    "sea_cards",
    4,
    13,
    10,
    1,
    null,
    6,
    10,
    null
   ],
   [
    247,
    19,
    "sum",
    83,
    54,
    91,
    100,
    null,
    92,
    77,
    null
   ],
   [
    248,
    19,
    "ranking",
    4,
    6,
    3,
    1,
    null,
    2,
    5,
    null
   ]
  ]
 },
 "20": {
  "date": "13.02.2024",
  "extensions": {
   "leaders": 1,
   "armada": 0,
   "edifice": 0,
   "cities": 0
  },
  "scoreboard": [
   [
    "row_id",
    "game_id",
    "points_type",
    "Pascal",
    "Stanley",
    "Elena",
    "Fabio",
    "Alan",
    "Rafael",
    "Leandro",
    "Yara"
   ],
   [
    249,
    20,
    "wonder",
    10,
    20,
    null,
    10,
    3,
    20,
    6,
    null
   ],
   [
    250,
    20,
    "money",
    4,
    7,
    null,
    3,
    1,
    0,
    6,
    null
   ],
   [
    251,
    20,
    "war",
    13,
    -3,
    null,
    -3,
    5,
    18,
    -4,
    null
   ],
   [
    252,
    20,
    "blue_cards",
    33,
    24,
    null,
    6,
    0,
    16,
    13,
    null
   ],
   [
    253,
    20,
    "yellow_cards",
    3,
    4,
    null,
    3,
    0,
    5,
    6,
    null
   ],
   [
    254,
    20,
    "green_cards",
    0,
    0,
    null,
    45,
    66,
    0,
    0,
    null
   ],
   [
    255,
    20,
    "purple_cards",
    5,
    10,
    null,
    0,
    0,
    8,
    24,
    null
   ],
   [
    256,
    20,
    "cities",
    null,
    null,
    null,
    null,
    null,
    null,
    null,
    null
   ],
   [
    257,
    20,
    "leaders",
    10,
    3,
    null,
    0,
    0,
    0,
    13,
    null
   ],
   [
    258,
    20,
    "sea_war",
    null,
    null,
    null,
    null,
    null,
    null,
    null,
    null
   ],
   [
    259,
    20,
    "sea_cards",
    null,
    null,
    null,
    null,
    null,
    null,
    null,
    null
   ],
   [
    260,
    20,
    "sum",
    78,
    65,
    null,
    64,
    75,
    67,
    64,
    null
   ],
   [
    261,
    20,
    "ranking",
    1,
    4,
    null,
    5,
    2,
    3,
    5,
    null
   ]
  ]
 },
 "21": {
  "date": "16.02.2024",
  "extensions": {
   "leaders": 1,
   "armada": 1,
   "edifice": 0,
   "cities": 0
  },
  "scoreboard": [
   [
    "row_id",
    "game_id",
    "points_type",
    "Pascal",
    "Stanley",
    "Elena",
    "Fabio",
    "Alan",
    "Rafael",
    "Leandro",
    "Yara"
   ],
   [
    262,
    21,
    "wonder",
    3,
    10,
    null,
    20,
    10,
    10,
    3,
    null
   ],
   [
    263,
    21,
    "money",
    17,
    10,
    null,
    4,
    0,
    11,
    0,
    null
   ],
   [
    264,
    21,
    "war",
    21,
    2,
    null,
    11,
    13,
    -2,
    -5,
    null
   ],
   [
    265,
    21,
    "blue_cards",
    7,
    30,
    null,
    6,
    10,
    28,
    17,
    null
   ],
   [
    266,
    21,
    "yellow_cards",
    32,
    11,
    null,
    4,
    0,
    8,
    0,
    null
   ],
   [
    267,
    21,
    "green_cards",
    0,
    0,
    null,
    47,
    36,
    1,
    16,
    null
   ],
   [
    268,
    21,
    "purple_cards",
    7,
    0,
    null,
    0,
    17,
    20,
    15,
    null
   ],
   [
    269,
    21,
    "cities",
    null,
    null,
    null,
    null,
    null,
    null,
    null,
    null
   ],
   [
    270,
    21,
    "leaders",
    31,
    0,
    null,
    0,
    4,
    0,
    2,
    null
   ],
   [
    271,
    21,
    "sea_war",
    6,
    -1,
    null,
    -5,
    -1,
    0,
    12,
    null
   ],
   [
    272,
    21,
    "sea_cards",
    2,
    8,
    null,
    4,
    10,
    10,
    2,
    null
   ],
   [
    273,
    21,
    "sum",
    126,
    70,
    null,
    91,
    99,
    86,
    62,
    null
   ],
   [
    274,
    21,
    "ranking",
    1,
    5,
    null,
    3,
    2,
    4,
    6,
    null
   ]
  ]
 },
 "22": {
  "date": "16.02.2024",
  "extensions": {
   "leaders": 1,
   "armada": 1,
   "edifice": 0,
   "cities": 1
  },
  "scoreboard": [
   [
    "row_id",
    "game_id",
    "points_type",
    "Pascal",
    "Stanley",
    "Elena",
    "Fabio",
    "Alan",
    "Rafael",
    "Leandro",
    "Yara"
   ],
   [
    275,
    22,
    "wonder",
    10,
    3,
    null,
    20,
    16,
    17,
    14,
    null
   ],
   [
    276,
    22,
    "money",
    8,
    3,
    null,
    4,
    8,
    21,
    1,
    null
   ],
   [
    277,
    22,
    "war",
    1,
    15,
    null,
    -3,
    7,
    -1,
    9,
    null
   ],
   [
    278,
    22,
    "blue_cards",
    13,
    21,
    null,
    14,
    5,
    18,
    29,
    null
   ],
   [
    279,
    22,
    "yellow_cards",
    6,
    9,
    null,
    4,
    14,
    3,
    3,
    null
   ],
   [
    280,
    22,
    "green_cards",
    37,
    0,
    null,
    71,
    1,
    0,
    0,
    null
   ],
   [
    281,
    22,
    "purple_cards",
    13,
    0,
    null,
    0,
    17,
    11,
    21,
    null
   ],
   [
    282,
    22,
    "cities",
    0,
    8,
    null,
    0,
    2,
    5,
    6,
    null
   ],
   [
    283,
    22,
    "leaders",
    0,
    0,
    null,
    4,
    13,
    5,
    10,
    null
   ],
   [
    284,
    22,
    "sea_war",
    3,
    4,
    null,
    -2,
    -2,
    15,
    -6,
    null
   ],
   [
    285,
    22,
    "sea_cards",
    7,
    10,
    null,
    13,
    6,
    6,
    6,
    null
   ],
   [
    286,
    22,
    "sum",
    98,
    73,
    null,
    125,
    87,
    100,
    93,
    null
   ],
   [
    287,
    22,
    "ranking",
    3,
    6,
    null,
    1,
    5,
    2,
    4,
    null
   ]
  ]
 }
}